nqrduck_spectrometer/__init__.py
nqrduck_spectrometer/base_spectrometer.py
nqrduck_spectrometer/base_spectrometer_controller.py
nqrduck_spectrometer/base_spectrometer_model.py
nqrduck_spectrometer/base_spectrometer_view.py
nqrduck_spectrometer/base_spectrometer_widget.py
nqrduck_spectrometer/controller.py
nqrduck_spectrometer/model.py
nqrduck_spectrometer/spectrometer.py
nqrduck_spectrometer/view.py
nqrduck_spectrometer/visual_settings.py
nqrduck_spectrometer/widget.py
nqrduck_spectrometer/resources/base_spectrometer_widget.ui
nqrduck_spectrometer/resources/spectrometer.ini
nqrduck_spectrometer/resources/spectrometer_widget.ui
nqrduck_spectrometer-0.0.13.dist-info/METADATA
nqrduck_spectrometer-0.0.13.dist-info/WHEEL
nqrduck_spectrometer-0.0.13.dist-info/entry_points.txt
nqrduck_spectrometer-0.0.13.dist-info/licenses/LICENSE
nqrduck_spectrometer-0.0.13.dist-info/RECORD
