Metadata-Version: 2.4
Name: nqrduck-spectrometer
Version: 0.0.13
Summary: A module for the NQRduck program (a simple python script™) to control different NQR/NMR spectrometers.
Project-URL: Homepage, https://nqrduck.cool
Project-URL: Bug Tracker, https://git.private.coffee/nqrduck/nqrduck-spectrometer/issues
Project-URL: Source Code, https://git.private.coffee/nqrduck/nqrduck-spectrometer
Author-email: jupfi <support@nqruck.cool>
License: MIT License
License-File: LICENSE
Classifier: License :: OSI Approved :: MIT License
Classifier: Operating System :: OS Independent
Classifier: Programming Language :: Python :: 3
Requires-Python: >=3.10
Requires-Dist: matplotlib
Requires-Dist: nqrduck
Requires-Dist: numpy
Requires-Dist: pyqt6
Requires-Dist: quackseq
Requires-Dist: scipy
Requires-Dist: sympy
Provides-Extra: dev
Requires-Dist: black; extra == 'dev'
Requires-Dist: pydocstyle; extra == 'dev'
Requires-Dist: pyupgrade; extra == 'dev'
Requires-Dist: ruff; extra == 'dev'
